syntheon/__init__.py
syntheon/main.py
syntheon/version.py
syntheon/converter/__init__.py
syntheon/converter/converter.py
syntheon/converter/dexed/__init__.py
syntheon/converter/dexed/dexed_constants.py
syntheon/converter/dexed/dexed_converter.py
syntheon/converter/vital/__init__.py
syntheon/converter/vital/vital_constants.py
syntheon/converter/vital/vital_converter.py
syntheon/inferencer/__init__.py
syntheon/inferencer/inferencer.py
syntheon/inferencer/dexed/__init__.py
syntheon/inferencer/dexed/dexed_inferencer.py
syntheon/inferencer/dexed/models/__init__.py
syntheon/inferencer/dexed/models/amp_utils.py
syntheon/inferencer/dexed/models/preprocessor.py
syntheon/inferencer/dexed/models/conf/__init__.py
syntheon/inferencer/dexed/models/conf/recipes/__init__.py
syntheon/inferencer/dexed/models/conf/recipes/model/__init__.py
syntheon/inferencer/dexed/models/conf/recipes/model/tcnres_f0ld_fmstr_noreverb.yaml
syntheon/inferencer/dexed/models/ddx7/__init__.py
syntheon/inferencer/dexed/models/ddx7/core.py
syntheon/inferencer/dexed/models/ddx7/loss_functions.py
syntheon/inferencer/dexed/models/ddx7/models.py
syntheon/inferencer/dexed/models/ddx7/spectral_ops.py
syntheon/inferencer/dexed/models/ddx7/synth.py
syntheon/inferencer/dexed/models/ddx7/data_utils/__init__.py
syntheon/inferencer/dexed/models/ddx7/data_utils/h5_dataset.py
syntheon/inferencer/dexed/models/ddx7/data_utils/preprocessor.py
syntheon/inferencer/vital/__init__.py
syntheon/inferencer/vital/config.yaml
syntheon/inferencer/vital/init.vital
syntheon/inferencer/vital/vital_inferencer.py
syntheon/inferencer/vital/checkpoints/__init__.py
syntheon/inferencer/vital/checkpoints/model.pt
syntheon/inferencer/vital/models/adsr_envelope.py
syntheon/inferencer/vital/models/core.py
syntheon/inferencer/vital/models/model.py
syntheon/inferencer/vital/models/preprocessor.py
syntheon/inferencer/vital/models/utils.py
syntheon/inferencer/vital/models/wavetable_synth.py
syntheon/utils/pitch_extractor.py
syntheon-0.0.2.dist-info/LICENSE
syntheon-0.0.2.dist-info/METADATA
syntheon-0.0.2.dist-info/WHEEL
syntheon-0.0.2.dist-info/top_level.txt
syntheon-0.0.2.dist-info/RECORD
