Metadata-Version: 2.1
Name: syntheon
Version: 0.0.2
Summary: Parameter inference of music synthesizers to simplify sound design process.
Home-page: https://github.com/gudgud96/syntheon
Author: Hao Hao Tan
Author-email: helloharry66@gmail.com
Requires-Python: >=3.7
License-File: LICENSE
Requires-Dist: librosa
Requires-Dist: tensorflow
Requires-Dist: torch ==1.12.1
Requires-Dist: torchvision ==0.13.1
Requires-Dist: mido
Requires-Dist: crepe ==0.0.12
Requires-Dist: hmmlearn ==0.2.7
Requires-Dist: nnAudio ==0.3.1
Requires-Dist: numpy
Requires-Dist: bitstruct
Requires-Dist: torchcrepe
Requires-Dist: torchcrepeV2
